<?xml version="1.0" encoding="utf-8" ?>
<Defs>

  <!-- ============================= Crawler ================================= -->

  <PawnKindDef Name="Crawler" ParentName="BaseMechanoidKind" Class="PawnKindDef">
    <defName>Mech_Crawler</defName>
    <label>crawler</label>
    <race>Mech_Crawler</race>
    <combatPower>35</combatPower>
    <defaultFactionType>Mechanoid</defaultFactionType>
    <aiAvoidCover>true</aiAvoidCover>
    <lifeStages>
      <li>
        <bodyGraphicData>
          <texPath>Things/Pawn/Mechanoid/Crawler</texPath>
          <graphicClass>Graphic_Multi</graphicClass>
          <drawSize>1.0</drawSize>
          <shadowData>
            <volume>(0.3, 0.3, 0.3)</volume>
          </shadowData>
        </bodyGraphicData>
      </li>
    </lifeStages>
    <weaponTags>
      <li>Melee</li>
    </weaponTags>
  </PawnKindDef>
 
  <!-- ============================= Skullywag ================================= -->

  <PawnKindDef Name="Skullywag" ParentName="BaseMechanoidKind" Class="PawnKindDef">
    <defName>Mech_Skullywag</defName>
    <label>skullywag</label>
    <race>Mech_Skullywag</race>
    <combatPower>120</combatPower>
    <defaultFactionType>Mechanoid</defaultFactionType>
    <aiAvoidCover>false</aiAvoidCover>
    <lifeStages>
      <li>
        <bodyGraphicData>
          <texPath>Things/Pawn/Mechanoid/Skullywag</texPath>
          <graphicClass>Graphic_Multi</graphicClass>
          <drawSize>1.25</drawSize>
          <shadowData>
            <volume>(0.4, 0.8, 0.4)</volume>
          </shadowData>
        </bodyGraphicData>
      </li>
    </lifeStages>
    <weaponTags>
      <li>Melee</li>
    </weaponTags>
  </PawnKindDef>

  <!-- ============================= Flamebot ================================= -->
  
  <PawnKindDef ParentName="BaseMechanoidKind" Class="PawnKindDef">
    <defName>Mech_Flamebot</defName>
    <label>flamebot</label>
    <race>Mech_Flamebot</race>
    <combatPower>200</combatPower>
    <isGoodBreacher>false</isGoodBreacher> <!-- So it's group is not considered for breach raids -->
    <defaultFactionType>Mechanoid</defaultFactionType>
	<weaponMoney>
      <min>9999</min>
      <max>9999</max>
    </weaponMoney>
    <weaponTags>
      <li>MechanoidFlamethrower</li>
    </weaponTags>
    <aiAvoidCover>true</aiAvoidCover>
    <lifeStages>
      <li>
        <bodyGraphicData>
          <texPath>Things/Pawn/Mechanoid/Flamebot</texPath>
          <graphicClass>Graphic_Multi</graphicClass>
          <drawSize>1.7</drawSize>
          <shadowData>
            <volume>(0.3, 0.3, 0.3)</volume>
          </shadowData>
        </bodyGraphicData>
      </li>
    </lifeStages>
  </PawnKindDef>
   
  <!-- ============================= Assaulter ================================= -->

  <PawnKindDef ParentName="BaseMechanoidKind" Class="PawnKindDef">
    <defName>Mech_Assaulter</defName>
    <label>assaulter</label>
    <race>Mech_Assaulter</race>
    <combatPower>240</combatPower>
    <defaultFactionType>Mechanoid</defaultFactionType>
	<weaponMoney>
      <min>9999</min>
      <max>9999</max>
    </weaponMoney>
    <weaponTags>
      <li>MechanoidGunAssaulter</li>
    </weaponTags>
    <aiAvoidCover>true</aiAvoidCover>
    <lifeStages>
      <li>
        <bodyGraphicData>
          <texPath>Things/Pawn/Mechanoid/Assaulter</texPath>
          <graphicClass>Graphic_Multi</graphicClass>
          <drawSize>1.25</drawSize>
          <shadowData>
            <volume>(0.4, 0.8, 0.4)</volume>
          </shadowData>
        </bodyGraphicData>
      </li>
    </lifeStages>
  </PawnKindDef>
  
  <!-- ============================= Mammoth ================================= -->
  
  <PawnKindDef ParentName="BaseMechanoidKind" Class="PawnKindDef">
	<defName>Mech_Mammoth</defName>
    <label>mammoth</label>
    <isGoodBreacher>false</isGoodBreacher> <!-- So it's group is not considered for breach raids -->
    <race>Mech_Mammoth</race>
    <combatPower>900</combatPower>
	<defaultFactionType>Mechanoid</defaultFactionType>
	<aiAvoidCover>true</aiAvoidCover>
    <lifeStages>
      <li>
        <bodyGraphicData>
          <texPath>Things/Pawn/Mechanoid/Mammoth</texPath>
          <graphicClass>Graphic_Multi</graphicClass>
          <drawSize>3</drawSize>
          <shadowData>
            <volume>(0.7, 0.9, 0.7)</volume>
          </shadowData>
		  <shaderType>Cutout</shaderType>
		</bodyGraphicData>
      </li>
    </lifeStages>
    <weaponTags>
      <li>Melee</li>
    </weaponTags>
  </PawnKindDef>  
</Defs>
